MANIFEST.in
README.rst
setup.cfg
setup.py
markdownify/__init__.py
tests/__init__.py
tests/test_advanced.py
tests/test_args.py
tests/test_basic.py
tests/test_conversions.py
tests/test_escaping.py
will_markdownify.egg-info/PKG-INFO
will_markdownify.egg-info/SOURCES.txt
will_markdownify.egg-info/dependency_links.txt
will_markdownify.egg-info/not-zip-safe
will_markdownify.egg-info/requires.txt
will_markdownify.egg-info/top_level.txt