Metadata-Version: 1.1
Name: will-markdownify
Version: 0.4.0
Summary: TEMPORARY fork, Convert HTML to markdown.
Home-page: http://github.com/heywill/python-markdownify
Author: Steven Skoczen (fork only).  Original author is Matthew Tretter
Author-email: steven@heywill.io
License: UNKNOWN
Download-URL: http://github.com/heywill/python-markdownify/tarball/master
Platform: UNKNOWN
Classifier: Environment :: Web Environment
Classifier: Framework :: Django
Classifier: Intended Audience :: Developers
Classifier: License :: OSI Approved :: BSD License
Classifier: Operating System :: OS Independent
Classifier: Programming Language :: Python :: 2.5
Classifier: Programming Language :: Python :: 2.6
Classifier: Programming Language :: Python :: 2.7
Classifier: Topic :: Utilities
